LICENSE
MANIFEST.in
README.md
setup.py
galcem/__init__.py
galcem/galcem.mplstyle
galcem/onezone.py
galcem.egg-info/PKG-INFO
galcem.egg-info/SOURCES.txt
galcem.egg-info/dependency_links.txt
galcem.egg-info/requires.txt
galcem.egg-info/top_level.txt
galcem/classes/__init__.py
galcem/classes/inputs.py
galcem/classes/integration.py
galcem/classes/morphology.py
galcem/classes/yields.py
galcem/input/observations/.DS_Store
galcem/input/observations/Hansen-12-2.txt
galcem/input/observations/Montelius-22.txt
galcem/input/observations/Reddy-06.txt
galcem/input/observations/Roriz-21.txt
galcem/input/observations/Wu-15.txt
galcem/input/observations/abund/.DS_Store
galcem/input/observations/abund/Adibekyan-12.txt
galcem/input/observations/abund/Akerman-04.txt
galcem/input/observations/abund/Andrievsky-07.txt
galcem/input/observations/abund/Andrievsky-08.txt
galcem/input/observations/abund/Andrievsky-10.txt
galcem/input/observations/abund/BattistiniBensby-15.txt
galcem/input/observations/abund/BattistiniBensby-16.txt
galcem/input/observations/abund/Bensby-05.txt
galcem/input/observations/abund/Bensby-14.txt
galcem/input/observations/abund/BensbyFeltzing-06.txt
galcem/input/observations/abund/Bihain-04.txt
galcem/input/observations/abund/Caffau-05.txt
galcem/input/observations/abund/Caffau-11.txt
galcem/input/observations/abund/Carretta-00.txt
galcem/input/observations/abund/Cayrel-04.txt
galcem/input/observations/abund/Cohen-13.txt
galcem/input/observations/abund/Cohen-CEMP-no-13.txt
galcem/input/observations/abund/Frebel-10.txt
galcem/input/observations/abund/Gratton-03.txt
galcem/input/observations/abund/Hansen-12.txt
galcem/input/observations/abund/Hinkel-14.txt
galcem/input/observations/abund/Ishigaki-12-13.txt
galcem/input/observations/abund/Jacobson-15.txt
galcem/input/observations/abund/Lai-08.txt
galcem/input/observations/abund/Maas-19.txt
galcem/input/observations/abund/Nissen-07.txt
galcem/input/observations/abund/Nissen-14.txt
galcem/input/observations/abund/Ramirez-13.txt
galcem/input/observations/abund/Reddy-03.txt
galcem/input/observations/abund/Reggiani-17.txt
galcem/input/observations/abund/Roederer-09.txt
