Metadata-Version: 2.1
Name: galcem
Version: 0.0.2b0
Summary: Galactic Chemical Evolution
Home-page: https://github.com/egjergo/GalCEM
Author: Eda Gjergo, Aleksei Sorokin
Author-email: eda.gjergo@gmail.com
License: GNU General Public License
Keywords: galactic,chemical,evolution,simulation
Platform: UNKNOWN
Classifier: Programming Language :: Python :: 3
Classifier: License :: OSI Approved :: Apache Software License
Classifier: Operating System :: OS Independent
Requires-Python: >=3.6
License-File: LICENSE
